pymail_aliyun/client_aliyun.py
pymail_aliyun/mail_utils.py
pymail_aliyun-0.1.15.dist-info/WHEEL
pymail_aliyun-0.1.15.dist-info/METADATA
pymail_aliyun-0.1.15.dist-info/RECORD
