Metadata-Version: 2.1
Name: pymail-aliyun
Version: 0.1.15
Summary: mail-aliyun wrapper
Author: zbjdonald
Author-email: service@yingchengtz.com
Requires-Python: >=3.7,<4.0
Classifier: Programming Language :: Python :: 3
Classifier: Programming Language :: Python :: 3.7
Classifier: Programming Language :: Python :: 3.8
Requires-Dist: beautifulsoup4 (>=4.8.1,<5.0.0)
Requires-Dist: imapclient (>=2.1.0,<3.0.0)
Requires-Dist: optionaldict (>=0.1.1,<0.2.0)
Requires-Dist: requests (>=2.22.0,<3.0.0)
Requires-Dist: selenium (>=3.141.0,<4.0.0)
Requires-Dist: simplejson (>=3.17.0,<4.0.0)
Requires-Dist: tqdm (>=4.41.1,<5.0.0)
